pyMETHES/__about__.py
pyMETHES/__init__.py
pyMETHES/config.py
pyMETHES/cross_section.py
pyMETHES/electrons.py
pyMETHES/energy_distribution.py
pyMETHES/gas_mixture.py
pyMETHES/monte_carlo.py
pyMETHES/output.py
pyMETHES/rate_coefficients.py
pyMETHES/simulation.py
pyMETHES/temporal_evolution.py
pyMETHES/transport_data.py
pyMETHES/utils.py
pyMETHES-0.2.0.dist-info/AUTHORS.rst
pyMETHES-0.2.0.dist-info/LICENSE
pyMETHES-0.2.0.dist-info/METADATA
pyMETHES-0.2.0.dist-info/WHEEL
pyMETHES-0.2.0.dist-info/top_level.txt
pyMETHES-0.2.0.dist-info/RECORD
