Metadata-Version: 2.1
Name: pyMETHES
Version: 0.2.0
Summary: Monte Carlo simulation of electron transport in low temperature plasmas
Home-page: https://gitlab.com/ethz_hvl/pymethes/
Author: Alise Chachereau, Kerry Jansen, Markus Niese, Martin Vahlensieck
Author-email: alisec@ethz.ch
License: GNU General Public License v3 (GPLv3)
Platform: UNKNOWN
Classifier: Development Status :: 2 - Pre-Alpha
Classifier: License :: OSI Approved :: GNU General Public License v3 (GPLv3)
Classifier: Programming Language :: Python
Classifier: Programming Language :: Python :: 3
Classifier: Programming Language :: Python :: 3.7
Classifier: Topic :: Scientific/Engineering :: Physics
Requires-Dist: json5
Requires-Dist: lxcat-data-parser
Requires-Dist: matplotlib
Requires-Dist: scipy
Requires-Dist: numpy
Requires-Dist: pandas
Requires-Dist: molmass
